{
  "app": {
    "products": [
      {
        "name": "default",
        "signingConfig": "default",
        "compatibleSdkVersion": "5.0.0(12)",
        "runtimeOS": "HarmonyOS",
        "buildOption": {
          "strictMode": {
            "caseSensitiveCheck": true,
            "useNormalizedOHMUrl": true
          }
        }
      }
    ],
    "buildModeSet": [
      {
        "name": "debug"
      },
      {
        "name": "release"
      }
    ],
    "signingConfigs": [
      {
        "name": "default",
        "type": "HarmonyOS",
        "material": {
          "storeFile": "OHOS_SIGNING_P12_FILE",
          "storePassword": "OHOS_SIGNING_P12_PWD",
          "keyAlias": "OHOS_SIGNING_KEY_ALIAS",
          "keyPassword": "OHOS_SIGNING_KEY_PWD",
          "signAlg": "OHOS_SIGNING_SIGN_ALG",
          "profile": "OHOS_SIGNING_PROFILE",
          "certpath": "OHOS_SIGNING_CER"
        }
      }
    ]
  },
  "modules": [
    {
      "name": "entry",
      "srcPath": "./entry",
      "targets": [
        {
          "name": "default",
          "applyToProducts": [
            "default"
          ]
        }
      ]
    }
  ]
}